[{"name":"npi","evidenceType":"string","typeFidelity":"precise"},{"name":"prscrbr_last_org_name","evidenceType":"string","typeFidelity":"precise"},{"name":"prscrbr_first_name","evidenceType":"string","typeFidelity":"precise"},{"name":"prscrbr_type","evidenceType":"string","typeFidelity":"precise"},{"name":"prscrbr_city","evidenceType":"string","typeFidelity":"precise"},{"name":"prscrbr_state_abrvtn","evidenceType":"string","typeFidelity":"precise"},{"name":"credential","evidenceType":"string","typeFidelity":"precise"},{"name":"status","evidenceType":"string","typeFidelity":"precise"},{"name":"sex","evidenceType":"string","typeFidelity":"precise"},{"name":"enumeration_date","evidenceType":"date","typeFidelity":"precise"},{"name":"last_updated","evidenceType":"date","typeFidelity":"precise"}]